{
  "id": "orach_chaim-686",
  "chapterLabel": "סימן undefinedפ״ו",
  "title": "שולחן ערוך, אורח חיים",
  "partName": "אורח חיים",
  "sections": [
    {
      "id": "orach_chaim-686-1",
      "section": 1,
      "text": "דין תענית אסתר. ובו ג סעיפים:בחנוכה ופורים מותר להתענות לפניהם ולאחריהם:"
    },
    {
      "id": "orach_chaim-686-2",
      "section": 2,
      "text": "מתענין בי\"ג באדר ואם חל פורים באחד בשבת מקדימין להתענות ביום חמישי: הגה ותענית זה אינו חובה לכן יש להקל בו לעת הצורך כגון מעוברות או מניקות או לחולה שאין בו סכנה ואפי' כואבי עינים שאם מצטערים הרבה לא יתענו ויפרעו אחר כך אבל שאר בריאים לא יפרשו מן הצבור [חדושי אגודה בשם מחזור ויטרי] ואם חל פורים ביום א' שמתענים ביום ה' שלפניו וחל בו ברית מילה מותר לאכול על המילה ולמחר ביום ו' יתענו האוכלים [הגהות מנהגים]:"
    },
    {
      "id": "orach_chaim-686-3",
      "section": 3,
      "text": "יש מתענים ג' ימים זכר לתענית אסתר:"
    }
  ]
}