{
  "id": "orach_chaim-528",
  "chapterLabel": "סימן undefinedכ״ח",
  "title": "שולחן ערוך, אורח חיים",
  "partName": "אורח חיים",
  "sections": [
    {
      "id": "orach_chaim-528-1",
      "section": 1,
      "text": "דיני עירובי חצרות בי\"ט. ובו ב סעיפים:יו\"ט אין צריך עירובי חצירות ושתופי מבואות אבל עירוב תחומין צריך וכל הלכות תחומין נתבארו בהלכות עירובי תחומין:"
    },
    {
      "id": "orach_chaim-528-2",
      "section": 2,
      "text": "יום טוב שחל להיות בערב שבת אין מערבין לא עירובי חצרות ולא עירובי תחומין (ואפי' אם הניח עירוב תבשילין) (ר\"ן פ\"ב דביצה) אבל אם נזכר ביום הראשון בשני ימים טובים של גליות יוכל לערב עירובי חצירות בתנאי אבל עירוב תחומין אין מניחין אותו ביו\"ט בתנאי:"
    }
  ]
}